futureboard/__init__.py
futureboard/base.py
futureboard/colors_utils.py
futureboard/congrats.py
futureboard/forms/__init__.py
futureboard/forms/congrats_employee.jinja2
futureboard/forms/congrats_employer.jinja2
futureboard/forms/job_thumbnail.jinja2
futureboard/job_post.py
futureboard-1.0.0.dist-info/WHEEL
futureboard-1.0.0.dist-info/METADATA
futureboard-1.0.0.dist-info/RECORD
