Metadata-Version: 2.1
Name: futureboard
Version: 1.0.0
Summary: 
Home-page: https://github.com/sakuguru/futureboard
Author: Nutchanon Ninyawee
Author-email: nutchanon@codustry.com
Requires-Python: >=3.8,<4.0
Classifier: Programming Language :: Python :: 3
Classifier: Programming Language :: Python :: 3.8
Classifier: Programming Language :: Python :: 3.9
Requires-Dist: Jinja2 (>=2.11.3,<3.0.0)
Requires-Dist: pydantic (>=1.7.3,<2.0.0)
Requires-Dist: snap-html (>=0.2.0,<0.3.0)
Project-URL: Repository, https://github.com/sakuguru/futureboard
